doorbirdpy/__init__.py
doorbirdpy/py.typed
doorbirdpy/schedule_entry.py
doorbirdpy-3.0.12.dist-info/licenses/LICENSE.txt
doorbirdpy-3.0.12.dist-info/METADATA
doorbirdpy-3.0.12.dist-info/WHEEL
doorbirdpy-3.0.12.dist-info/top_level.txt
doorbirdpy-3.0.12.dist-info/RECORD
