Metadata-Version: 2.4
Name: DoorBirdPy
Version: 3.0.12
Summary: Python wrapper for the DoorBird LAN API
Home-page: https://gitlab.com/klikini/doorbirdpy
Download-URL: https://gitlab.com/klikini/doorbirdpy/-/archive/master/doorbirdpy-master.zip
Author: Andy Castille
Author-email: andy@robiotic.net
Maintainer: J. Nick Koston
Maintainer-email: nick@koston.org
License: MIT
Platform: Cross Platform
Requires-Python: >=3.9
License-File: LICENSE.txt
Requires-Dist: aiohttp
Requires-Dist: tenacity>=8
Dynamic: author
Dynamic: author-email
Dynamic: download-url
Dynamic: home-page
Dynamic: license
Dynamic: license-file
Dynamic: maintainer
Dynamic: maintainer-email
Dynamic: platform
Dynamic: requires-dist
Dynamic: requires-python
Dynamic: summary
